human_say/__init__.py
human_say/say_goodbye.py
human_say/say_hello.py
human_say-0.1.0.dist-info/METADATA
human_say-0.1.0.dist-info/WHEEL
human_say-0.1.0.dist-info/RECORD
