Metadata-Version: 2.4
Name: human-say
Version: 0.1.0
Summary: A simple Python package for greeting and farewell messages
Project-URL: Homepage, https://github.com/abbasi0abolfazl/hello_world_pypi.git
Author-email: Abolfazl Abbasi <a.abbasi5775@gmail.com>
License: MIT License
Classifier: Intended Audience :: Developers
Classifier: License :: OSI Approved :: MIT License
Classifier: Natural Language :: English
Classifier: Operating System :: OS Independent
Classifier: Programming Language :: Python :: 3
Classifier: Programming Language :: Python :: 3.11
Requires-Python: >=3.11
Requires-Dist: twine>=6.1.0
